{
  "id": "7644863912545881366",
  "formats": [
    {
      "ext": "mp4",
      "vcodec": "h264",
      "acodec": "aac",
      "format_id": "download",
      "url": "https://v16-webapp-prime.tiktok.com/video/tos/no1a/tos-no1a-ve-0068c001-no/o0EWMmofABGYgjfRuAAAFgRYwAcQYe3Ggb4fqm/?a=1988&bti=ODszNWYuMDE6&&bt=498&eid=5376&ft=-Csk_mwKPD12NLM-Kn-Ux~7vSY3W3wv25UcAp&mime_type=video_mp4&rc=ZWU8MzM3ZWhmO2hnZDw4aEBpM3BmeXQ5cnQzOzMzbzczNUBfNS1eMGFfNmExNDA0Y15fYSMxb3JhMmQ0MWBhLS1kMTFzcw%3D%3D&expire=1780829179&l=202606051045589FCA2984B9C2E91CC752&ply_type=2&policy=2&signature=17c2320081f4e3e4918cc53475c18d34&tk=tt_chain_token&btag=e000b8000",
      "format_note": "watermarked",
      "preference": -2,
      "protocol": "https",
      "video_ext": "mp4",
      "audio_ext": "none",
      "vbr": null,
      "abr": null,
      "tbr": null,
      "resolution": null,
      "dynamic_range": "SDR",
      "aspect_ratio": null,
      "filesize_approx": null,
      "cookies": "ttwid=1%7CEYdUHAzYXjaML9H0KdjuGOodVOjjysH4XUSmjU0KLNA%7C1780656358%7Cdd45b32ef16c36078e3f6c47a13ed1c9010353e89044df53c1707de8c49d9013; Domain=.tiktok.com; Path=/; Secure; Expires=1811760358; tt_csrf_token=R2BYlpRK-P2Qh-lO2NBUgdzZCG-vGFi7gkH8; Domain=.tiktok.com; Path=/; Secure; tt_chain_token=\"aljUYq5Z3u8APiqwo6JJjw==\"; Domain=.tiktok.com; Path=/; Secure; Expires=1796208358",
      "http_headers": {
        "User-Agent": "Mozilla/5.0 (Windows NT 10.0; Win64; x64) AppleWebKit/537.36 (KHTML, like Gecko) Chrome/140.0.0.0 Safari/537.36",
        "Accept": "text/html,application/xhtml+xml,application/xml;q=0.9,*/*;q=0.8",
        "Accept-Language": "en-us,en;q=0.5",
        "Sec-Fetch-Mode": "navigate",
        "Referer": "https://www.tiktok.com/@docmap/video/7644863912545881366"
      },
      "format": "download - unknown (watermarked)"
    },
    {
      "ext": "mp4",
      "vcodec": "h264",
      "acodec": "aac",
      "format_id": "h264_540p_485213-0",
      "tbr": 485,
      "quality": 1,
      "format_note": null,
      "preference": -1,
      "filesize": 1230805,
      "width": 576,
      "height": 1024,
      "url": "https://v16-webapp-prime.tiktok.com/video/tos/no1a/tos-no1a-ve-0068c001-no/okMhfADGIAEF1FRzq32oJQkEgIRYBfEEBL0AEN/?a=1988&bti=ODszNWYuMDE6&&bt=473&ft=-Csk_mwKPD12NLM-Kn-Ux~7vSY3W3wv25UcAp&mime_type=video_mp4&rc=O2RmZ2U5PDxoaDg0NTk3ZEBpM3BmeXQ5cnQzOzMzbzczNUA1LzYtNDMzXzExYl4vMmNgYSMxb3JhMmQ0MWBhLS1kMTFzcw%3D%3D&expire=1780829179&l=202606051045589FCA2984B9C2E91CC752&ply_type=2&policy=2&signature=3ea693df57e3b27610e76be456a20401&tk=tt_chain_token&btag=e000b8000",
      "protocol": "https",
      "video_ext": "mp4",
      "audio_ext": "none",
      "vbr": null,
      "abr": null,
      "resolution": "576x1024",
      "dynamic_range": "SDR",
      "aspect_ratio": 0.56,
      "cookies": "ttwid=1%7CEYdUHAzYXjaML9H0KdjuGOodVOjjysH4XUSmjU0KLNA%7C1780656358%7Cdd45b32ef16c36078e3f6c47a13ed1c9010353e89044df53c1707de8c49d9013; Domain=.tiktok.com; Path=/; Secure; Expires=1811760358; tt_csrf_token=R2BYlpRK-P2Qh-lO2NBUgdzZCG-vGFi7gkH8; Domain=.tiktok.com; Path=/; Secure; tt_chain_token=\"aljUYq5Z3u8APiqwo6JJjw==\"; Domain=.tiktok.com; Path=/; Secure; Expires=1796208358",
      "http_headers": {
        "User-Agent": "Mozilla/5.0 (Windows NT 10.0; Win64; x64) AppleWebKit/537.36 (KHTML, like Gecko) Chrome/140.0.0.0 Safari/537.36",
        "Accept": "text/html,application/xhtml+xml,application/xml;q=0.9,*/*;q=0.8",
        "Accept-Language": "en-us,en;q=0.5",
        "Sec-Fetch-Mode": "navigate",
        "Referer": "https://www.tiktok.com/@docmap/video/7644863912545881366"
      },
      "format": "h264_540p_485213-0 - 576x1024"
    },
    {
      "ext": "mp4",
      "vcodec": "h264",
      "acodec": "aac",
      "format_id": "h264_540p_485213-1",
      "tbr": 485,
      "quality": 1,
      "format_note": null,
      "preference": -1,
      "filesize": 1230805,
      "width": 576,
      "height": 1024,
      "url": "https://v19-webapp-prime.tiktok.com/video/tos/no1a/tos-no1a-ve-0068c001-no/okMhfADGIAEF1FRzq32oJQkEgIRYBfEEBL0AEN/?a=1988&bti=ODszNWYuMDE6&&bt=473&ft=-Csk_mwKPD12NLM-Kn-Ux~7vSY3W3wv25UcAp&mime_type=video_mp4&rc=O2RmZ2U5PDxoaDg0NTk3ZEBpM3BmeXQ5cnQzOzMzbzczNUA1LzYtNDMzXzExYl4vMmNgYSMxb3JhMmQ0MWBhLS1kMTFzcw%3D%3D&expire=1780829179&l=202606051045589FCA2984B9C2E91CC752&ply_type=2&policy=2&signature=3ea693df57e3b27610e76be456a20401&tk=tt_chain_token&btag=e000b8000",
      "protocol": "https",
      "video_ext": "mp4",
      "audio_ext": "none",
      "vbr": null,
      "abr": null,
      "resolution": "576x1024",
      "dynamic_range": "SDR",
      "aspect_ratio": 0.56,
      "cookies": "ttwid=1%7CEYdUHAzYXjaML9H0KdjuGOodVOjjysH4XUSmjU0KLNA%7C1780656358%7Cdd45b32ef16c36078e3f6c47a13ed1c9010353e89044df53c1707de8c49d9013; Domain=.tiktok.com; Path=/; Secure; Expires=1811760358; tt_csrf_token=R2BYlpRK-P2Qh-lO2NBUgdzZCG-vGFi7gkH8; Domain=.tiktok.com; Path=/; Secure; tt_chain_token=\"aljUYq5Z3u8APiqwo6JJjw==\"; Domain=.tiktok.com; Path=/; Secure; Expires=1796208358",
      "http_headers": {
        "User-Agent": "Mozilla/5.0 (Windows NT 10.0; Win64; x64) AppleWebKit/537.36 (KHTML, like Gecko) Chrome/140.0.0.0 Safari/537.36",
        "Accept": "text/html,application/xhtml+xml,application/xml;q=0.9,*/*;q=0.8",
        "Accept-Language": "en-us,en;q=0.5",
        "Sec-Fetch-Mode": "navigate",
        "Referer": "https://www.tiktok.com/@docmap/video/7644863912545881366"
      },
      "format": "h264_540p_485213-1 - 576x1024"
    },
    {
      "ext": "mp4",
      "vcodec": "h265",
      "acodec": "aac",
      "format_id": "bytevc1_540p_215694-0",
      "tbr": 215,
      "quality": 1,
      "format_note": null,
      "preference": -1,
      "filesize": 547137,
      "width": 576,
      "height": 1024,
      "url": "https://v16-webapp-prime.tiktok.com/video/tos/no1a/tos-no1a-ve-0068-no/ocIUYqNEsBAWpgRf0zEAEFEFJAD92GIt3fIo8k/?a=1988&bti=ODszNWYuMDE6&&bt=210&ft=-Csk_mwKPD12NLM-Kn-Ux~7vSY3W3wv25UcAp&mime_type=video_mp4&rc=OGU5OzloPDM0ZDtmZ2ZkOUBpM3BmeXQ5cnQzOzMzbzczNUAvNjQyYS9fX18xYC0uXmNgYSMxb3JhMmQ0MWBhLS1kMTFzcw%3D%3D&expire=1780829179&l=202606051045589FCA2984B9C2E91CC752&ply_type=2&policy=2&signature=b1cc30e08d3912252588d5d7a181bc44&tk=tt_chain_token&btag=e000b8000",
      "protocol": "https",
      "video_ext": "mp4",
      "audio_ext": "none",
      "vbr": null,
      "abr": null,
      "resolution": "576x1024",
      "dynamic_range": "SDR",
      "aspect_ratio": 0.56,
      "cookies": "ttwid=1%7CEYdUHAzYXjaML9H0KdjuGOodVOjjysH4XUSmjU0KLNA%7C1780656358%7Cdd45b32ef16c36078e3f6c47a13ed1c9010353e89044df53c1707de8c49d9013; Domain=.tiktok.com; Path=/; Secure; Expires=1811760358; tt_csrf_token=R2BYlpRK-P2Qh-lO2NBUgdzZCG-vGFi7gkH8; Domain=.tiktok.com; Path=/; Secure; tt_chain_token=\"aljUYq5Z3u8APiqwo6JJjw==\"; Domain=.tiktok.com; Path=/; Secure; Expires=1796208358",
      "http_headers": {
        "User-Agent": "Mozilla/5.0 (Windows NT 10.0; Win64; x64) AppleWebKit/537.36 (KHTML, like Gecko) Chrome/140.0.0.0 Safari/537.36",
        "Accept": "text/html,application/xhtml+xml,application/xml;q=0.9,*/*;q=0.8",
        "Accept-Language": "en-us,en;q=0.5",
        "Sec-Fetch-Mode": "navigate",
        "Referer": "https://www.tiktok.com/@docmap/video/7644863912545881366"
      },
      "format": "bytevc1_540p_215694-0 - 576x1024"
    },
    {
      "ext": "mp4",
      "vcodec": "h265",
      "acodec": "aac",
      "format_id": "bytevc1_540p_215694-1",
      "tbr": 215,
      "quality": 1,
      "format_note": null,
      "preference": -1,
      "filesize": 547137,
      "width": 576,
      "height": 1024,
      "url": "https://v19-webapp-prime.tiktok.com/video/tos/no1a/tos-no1a-ve-0068-no/ocIUYqNEsBAWpgRf0zEAEFEFJAD92GIt3fIo8k/?a=1988&bti=ODszNWYuMDE6&&bt=210&ft=-Csk_mwKPD12NLM-Kn-Ux~7vSY3W3wv25UcAp&mime_type=video_mp4&rc=OGU5OzloPDM0ZDtmZ2ZkOUBpM3BmeXQ5cnQzOzMzbzczNUAvNjQyYS9fX18xYC0uXmNgYSMxb3JhMmQ0MWBhLS1kMTFzcw%3D%3D&expire=1780829179&l=202606051045589FCA2984B9C2E91CC752&ply_type=2&policy=2&signature=b1cc30e08d3912252588d5d7a181bc44&tk=tt_chain_token&btag=e000b8000",
      "protocol": "https",
      "video_ext": "mp4",
      "audio_ext": "none",
      "vbr": null,
      "abr": null,
      "resolution": "576x1024",
      "dynamic_range": "SDR",
      "aspect_ratio": 0.56,
      "cookies": "ttwid=1%7CEYdUHAzYXjaML9H0KdjuGOodVOjjysH4XUSmjU0KLNA%7C1780656358%7Cdd45b32ef16c36078e3f6c47a13ed1c9010353e89044df53c1707de8c49d9013; Domain=.tiktok.com; Path=/; Secure; Expires=1811760358; tt_csrf_token=R2BYlpRK-P2Qh-lO2NBUgdzZCG-vGFi7gkH8; Domain=.tiktok.com; Path=/; Secure; tt_chain_token=\"aljUYq5Z3u8APiqwo6JJjw==\"; Domain=.tiktok.com; Path=/; Secure; Expires=1796208358",
      "http_headers": {
        "User-Agent": "Mozilla/5.0 (Windows NT 10.0; Win64; x64) AppleWebKit/537.36 (KHTML, like Gecko) Chrome/140.0.0.0 Safari/537.36",
        "Accept": "text/html,application/xhtml+xml,application/xml;q=0.9,*/*;q=0.8",
        "Accept-Language": "en-us,en;q=0.5",
        "Sec-Fetch-Mode": "navigate",
        "Referer": "https://www.tiktok.com/@docmap/video/7644863912545881366"
      },
      "format": "bytevc1_540p_215694-1 - 576x1024"
    },
    {
      "ext": "mp4",
      "vcodec": "h265",
      "acodec": "aac",
      "format_id": "bytevc1_720p_270723-0",
      "tbr": 270,
      "quality": 2,
      "format_note": null,
      "preference": -1,
      "filesize": 686723,
      "width": 720,
      "height": 1280,
      "url": "https://v16-webapp-prime.tiktok.com/video/tos/no1a/tos-no1a-ve-0068c001-no/okhbQQLeQfIRusQxLUGAITMpjvUADDYI9AImeD/?a=1988&bti=ODszNWYuMDE6&&bt=264&ft=-Csk_mwKPD12NLM-Kn-Ux~7vSY3W3wv25UcAp&mime_type=video_mp4&rc=NjlnaDxlPDU4NDlpNGc3OkBpM3BmeXQ5cnQzOzMzbzczNUBeXy1gLmIzX2ExYy8wMC1gYSMxb3JhMmQ0MWBhLS1kMTFzcw%3D%3D&expire=1780829179&l=202606051045589FCA2984B9C2E91CC752&ply_type=2&policy=2&signature=9224c5c1c3d19c33af84b457dfc2b8dc&tk=tt_chain_token&btag=e000b8000",
      "protocol": "https",
      "video_ext": "mp4",
      "audio_ext": "none",
      "vbr": null,
      "abr": null,
      "resolution": "720x1280",
      "dynamic_range": "SDR",
      "aspect_ratio": 0.56,
      "cookies": "ttwid=1%7CEYdUHAzYXjaML9H0KdjuGOodVOjjysH4XUSmjU0KLNA%7C1780656358%7Cdd45b32ef16c36078e3f6c47a13ed1c9010353e89044df53c1707de8c49d9013; Domain=.tiktok.com; Path=/; Secure; Expires=1811760358; tt_csrf_token=R2BYlpRK-P2Qh-lO2NBUgdzZCG-vGFi7gkH8; Domain=.tiktok.com; Path=/; Secure; tt_chain_token=\"aljUYq5Z3u8APiqwo6JJjw==\"; Domain=.tiktok.com; Path=/; Secure; Expires=1796208358",
      "http_headers": {
        "User-Agent": "Mozilla/5.0 (Windows NT 10.0; Win64; x64) AppleWebKit/537.36 (KHTML, like Gecko) Chrome/140.0.0.0 Safari/537.36",
        "Accept": "text/html,application/xhtml+xml,application/xml;q=0.9,*/*;q=0.8",
        "Accept-Language": "en-us,en;q=0.5",
        "Sec-Fetch-Mode": "navigate",
        "Referer": "https://www.tiktok.com/@docmap/video/7644863912545881366"
      },
      "format": "bytevc1_720p_270723-0 - 720x1280"
    },
    {
      "ext": "mp4",
      "vcodec": "h265",
      "acodec": "aac",
      "format_id": "bytevc1_720p_270723-1",
      "tbr": 270,
      "quality": 2,
      "format_note": null,
      "preference": -1,
      "filesize": 686723,
      "width": 720,
      "height": 1280,
      "url": "https://v19-webapp-prime.tiktok.com/video/tos/no1a/tos-no1a-ve-0068c001-no/okhbQQLeQfIRusQxLUGAITMpjvUADDYI9AImeD/?a=1988&bti=ODszNWYuMDE6&&bt=264&ft=-Csk_mwKPD12NLM-Kn-Ux~7vSY3W3wv25UcAp&mime_type=video_mp4&rc=NjlnaDxlPDU4NDlpNGc3OkBpM3BmeXQ5cnQzOzMzbzczNUBeXy1gLmIzX2ExYy8wMC1gYSMxb3JhMmQ0MWBhLS1kMTFzcw%3D%3D&expire=1780829179&l=202606051045589FCA2984B9C2E91CC752&ply_type=2&policy=2&signature=9224c5c1c3d19c33af84b457dfc2b8dc&tk=tt_chain_token&btag=e000b8000",
      "protocol": "https",
      "video_ext": "mp4",
      "audio_ext": "none",
      "vbr": null,
      "abr": null,
      "resolution": "720x1280",
      "dynamic_range": "SDR",
      "aspect_ratio": 0.56,
      "cookies": "ttwid=1%7CEYdUHAzYXjaML9H0KdjuGOodVOjjysH4XUSmjU0KLNA%7C1780656358%7Cdd45b32ef16c36078e3f6c47a13ed1c9010353e89044df53c1707de8c49d9013; Domain=.tiktok.com; Path=/; Secure; Expires=1811760358; tt_csrf_token=R2BYlpRK-P2Qh-lO2NBUgdzZCG-vGFi7gkH8; Domain=.tiktok.com; Path=/; Secure; tt_chain_token=\"aljUYq5Z3u8APiqwo6JJjw==\"; Domain=.tiktok.com; Path=/; Secure; Expires=1796208358",
      "http_headers": {
        "User-Agent": "Mozilla/5.0 (Windows NT 10.0; Win64; x64) AppleWebKit/537.36 (KHTML, like Gecko) Chrome/140.0.0.0 Safari/537.36",
        "Accept": "text/html,application/xhtml+xml,application/xml;q=0.9,*/*;q=0.8",
        "Accept-Language": "en-us,en;q=0.5",
        "Sec-Fetch-Mode": "navigate",
        "Referer": "https://www.tiktok.com/@docmap/video/7644863912545881366"
      },
      "format": "bytevc1_720p_270723-1 - 720x1280"
    },
    {
      "ext": "mp4",
      "vcodec": "h265",
      "acodec": "aac",
      "format_id": "bytevc1_1080p_398613-0",
      "tbr": 398,
      "quality": 3,
      "format_note": null,
      "preference": -1,
      "filesize": 1011132,
      "width": 1080,
      "height": 1920,
      "url": "https://v16-webapp-prime.tiktok.com/video/tos/no1a/tos-no1a-ve-0068c001-no/oI4EFGokMEAA2bYfNrhJYfPCIgE03BDwqIzRbF/?a=1988&bti=ODszNWYuMDE6&&bt=389&ft=-Csk_mwKPD12NLM-Kn-Ux~7vSY3W3wv25UcAp&mime_type=video_mp4&rc=ZDxnOztoOjxnaDYzZmc4M0BpM3BmeXQ5cnQzOzMzbzczNUAyYmI2MzViXjExMDNiMjM1YSMxb3JhMmQ0MWBhLS1kMTFzcw%3D%3D&expire=1780829179&l=202606051045589FCA2984B9C2E91CC752&ply_type=2&policy=2&signature=3cb95cb7b13314c929d83577d92d4fbd&tk=tt_chain_token&btag=e000b8000",
      "protocol": "https",
      "video_ext": "mp4",
      "audio_ext": "none",
      "vbr": null,
      "abr": null,
      "resolution": "1080x1920",
      "dynamic_range": "SDR",
      "aspect_ratio": 0.56,
      "cookies": "ttwid=1%7CEYdUHAzYXjaML9H0KdjuGOodVOjjysH4XUSmjU0KLNA%7C1780656358%7Cdd45b32ef16c36078e3f6c47a13ed1c9010353e89044df53c1707de8c49d9013; Domain=.tiktok.com; Path=/; Secure; Expires=1811760358; tt_csrf_token=R2BYlpRK-P2Qh-lO2NBUgdzZCG-vGFi7gkH8; Domain=.tiktok.com; Path=/; Secure; tt_chain_token=\"aljUYq5Z3u8APiqwo6JJjw==\"; Domain=.tiktok.com; Path=/; Secure; Expires=1796208358",
      "http_headers": {
        "User-Agent": "Mozilla/5.0 (Windows NT 10.0; Win64; x64) AppleWebKit/537.36 (KHTML, like Gecko) Chrome/140.0.0.0 Safari/537.36",
        "Accept": "text/html,application/xhtml+xml,application/xml;q=0.9,*/*;q=0.8",
        "Accept-Language": "en-us,en;q=0.5",
        "Sec-Fetch-Mode": "navigate",
        "Referer": "https://www.tiktok.com/@docmap/video/7644863912545881366"
      },
      "format": "bytevc1_1080p_398613-0 - 1080x1920"
    },
    {
      "ext": "mp4",
      "vcodec": "h265",
      "acodec": "aac",
      "format_id": "bytevc1_1080p_398613-1",
      "tbr": 398,
      "quality": 3,
      "format_note": null,
      "preference": -1,
      "filesize": 1011132,
      "width": 1080,
      "height": 1920,
      "url": "https://v19-webapp-prime.tiktok.com/video/tos/no1a/tos-no1a-ve-0068c001-no/oI4EFGokMEAA2bYfNrhJYfPCIgE03BDwqIzRbF/?a=1988&bti=ODszNWYuMDE6&&bt=389&ft=-Csk_mwKPD12NLM-Kn-Ux~7vSY3W3wv25UcAp&mime_type=video_mp4&rc=ZDxnOztoOjxnaDYzZmc4M0BpM3BmeXQ5cnQzOzMzbzczNUAyYmI2MzViXjExMDNiMjM1YSMxb3JhMmQ0MWBhLS1kMTFzcw%3D%3D&expire=1780829179&l=202606051045589FCA2984B9C2E91CC752&ply_type=2&policy=2&signature=3cb95cb7b13314c929d83577d92d4fbd&tk=tt_chain_token&btag=e000b8000",
      "protocol": "https",
      "video_ext": "mp4",
      "audio_ext": "none",
      "vbr": null,
      "abr": null,
      "resolution": "1080x1920",
      "dynamic_range": "SDR",
      "aspect_ratio": 0.56,
      "cookies": "ttwid=1%7CEYdUHAzYXjaML9H0KdjuGOodVOjjysH4XUSmjU0KLNA%7C1780656358%7Cdd45b32ef16c36078e3f6c47a13ed1c9010353e89044df53c1707de8c49d9013; Domain=.tiktok.com; Path=/; Secure; Expires=1811760358; tt_csrf_token=R2BYlpRK-P2Qh-lO2NBUgdzZCG-vGFi7gkH8; Domain=.tiktok.com; Path=/; Secure; tt_chain_token=\"aljUYq5Z3u8APiqwo6JJjw==\"; Domain=.tiktok.com; Path=/; Secure; Expires=1796208358",
      "http_headers": {
        "User-Agent": "Mozilla/5.0 (Windows NT 10.0; Win64; x64) AppleWebKit/537.36 (KHTML, like Gecko) Chrome/140.0.0.0 Safari/537.36",
        "Accept": "text/html,application/xhtml+xml,application/xml;q=0.9,*/*;q=0.8",
        "Accept-Language": "en-us,en;q=0.5",
        "Sec-Fetch-Mode": "navigate",
        "Referer": "https://www.tiktok.com/@docmap/video/7644863912545881366"
      },
      "format": "bytevc1_1080p_398613-1 - 1080x1920"
    }
  ],
  "subtitles": {},
  "http_headers": {
    "User-Agent": "Mozilla/5.0 (Windows NT 10.0; Win64; x64) AppleWebKit/537.36 (KHTML, like Gecko) Chrome/140.0.0.0 Safari/537.36",
    "Accept": "text/html,application/xhtml+xml,application/xml;q=0.9,*/*;q=0.8",
    "Accept-Language": "en-us,en;q=0.5",
    "Sec-Fetch-Mode": "navigate",
    "Referer": "https://www.tiktok.com/@docmap/video/7644863912545881366"
  },
  "channel": "docmap",
  "channel_id": "MS4wLjABAAAAFJURMLSR0Pg7ewlOr04kHpZUsz75ua2wQVK37080oHzNn_-Oy_nrVhtTz2GuyTZg",
  "uploader": "docmap",
  "uploader_id": "7566624635910554626",
  "channel_url": "https://www.tiktok.com/@MS4wLjABAAAAFJURMLSR0Pg7ewlOr04kHpZUsz75ua2wQVK37080oHzNn_-Oy_nrVhtTz2GuyTZg",
  "uploader_url": "https://www.tiktok.com/@docmap",
  "track": "where is my mind (piano version)",
  "album": "where is my mind (piano version)",
  "artists": [
    "your movie soundtrack"
  ],
  "duration": 20,
  "title": "Your MRI is only as useful as the person reading it. For endo, that m...",
  "description": "Your MRI is only as useful as the person reading it. For endo, that matters more than most people reglize.  #endometriosis #endoawareness",
  "timestamp": 1779958600,
  "view_count": 17500,
  "like_count": 1072,
  "repost_count": 88,
  "comment_count": 27,
  "save_count": 253,
  "thumbnails": [
    {
      "id": "dynamicCover",
      "url": "https://p16-common-sign.tiktokcdn-eu.com/tos-no1a-p-0037-no/oYPzAA33DIg0IY0JANFBkURo2BfmqoFIEmgfEG~tplv-tiktokx-origin.image?dr=10395&x-expires=1780826400&x-signature=yHtDaOu%2FtkWbnQddO5b8TEcuP6s%3D&t=4d5b0474&ps=13740610&shp=81f88b70&shcp=43f4a2f9&idc=no1a",
      "preference": -2
    },
    {
      "id": "cover",
      "url": "https://p16-common-sign.tiktokcdn-eu.com/tos-no1a-p-0037-no/ogExzZREIFAf0I4YEq1gfI3NkBFJ2AGDAOIou0~tplv-tiktokx-origin.image?dr=10395&x-expires=1780826400&x-signature=6LXQaIllk5F69V%2BAo0cH3z1%2Fjn4%3D&t=4d5b0474&ps=13740610&shp=81f88b70&shcp=43f4a2f9&idc=no1a",
      "preference": -1
    },
    {
      "id": "originCover",
      "url": "https://p16-common-sign.tiktokcdn-eu.com/tos-no1a-p-0037-no/o0mwTUfvIcrAALKgbAIQ4ALBeRTMDQGpIQpejs~tplv-tiktokx-origin.image?dr=10395&x-expires=1780826400&x-signature=iDgvgtS%2FbEH1zC%2BkioA0LzaydG0%3D&t=4d5b0474&ps=13740610&shp=81f88b70&shcp=43f4a2f9&idc=no1a",
      "preference": -1
    }
  ],
  "webpage_url": "https://www.tiktok.com/@docmap/video/7644863912545881366",
  "original_url": "https://www.tiktok.com/@docmap/video/7644863912545881366",
  "webpage_url_basename": "7644863912545881366",
  "webpage_url_domain": "tiktok.com",
  "extractor": "TikTok",
  "extractor_key": "TikTok",
  "playlist": null,
  "playlist_index": null,
  "thumbnail": "https://p16-common-sign.tiktokcdn-eu.com/tos-no1a-p-0037-no/o0mwTUfvIcrAALKgbAIQ4ALBeRTMDQGpIQpejs~tplv-tiktokx-origin.image?dr=10395&x-expires=1780826400&x-signature=iDgvgtS%2FbEH1zC%2BkioA0LzaydG0%3D&t=4d5b0474&ps=13740610&shp=81f88b70&shcp=43f4a2f9&idc=no1a",
  "display_id": "7644863912545881366",
  "fulltitle": "Your MRI is only as useful as the person reading it. For endo, that m...",
  "duration_string": "20",
  "upload_date": "20260528",
  "release_year": null,
  "artist": "your movie soundtrack",
  "requested_subtitles": null,
  "_has_drm": null,
  "epoch": 1780656359,
  "ext": "mp4",
  "vcodec": "h265",
  "acodec": "aac",
  "format_id": "bytevc1_1080p_398613-1",
  "tbr": 398,
  "quality": 3,
  "format_note": null,
  "preference": -1,
  "filesize": 1011132,
  "width": 1080,
  "height": 1920,
  "url": "https://v19-webapp-prime.tiktok.com/video/tos/no1a/tos-no1a-ve-0068c001-no/oI4EFGokMEAA2bYfNrhJYfPCIgE03BDwqIzRbF/?a=1988&bti=ODszNWYuMDE6&&bt=389&ft=-Csk_mwKPD12NLM-Kn-Ux~7vSY3W3wv25UcAp&mime_type=video_mp4&rc=ZDxnOztoOjxnaDYzZmc4M0BpM3BmeXQ5cnQzOzMzbzczNUAyYmI2MzViXjExMDNiMjM1YSMxb3JhMmQ0MWBhLS1kMTFzcw%3D%3D&expire=1780829179&l=202606051045589FCA2984B9C2E91CC752&ply_type=2&policy=2&signature=3cb95cb7b13314c929d83577d92d4fbd&tk=tt_chain_token&btag=e000b8000",
  "protocol": "https",
  "video_ext": "mp4",
  "audio_ext": "none",
  "vbr": null,
  "abr": null,
  "resolution": "1080x1920",
  "dynamic_range": "SDR",
  "aspect_ratio": 0.56,
  "cookies": "ttwid=1%7CEYdUHAzYXjaML9H0KdjuGOodVOjjysH4XUSmjU0KLNA%7C1780656358%7Cdd45b32ef16c36078e3f6c47a13ed1c9010353e89044df53c1707de8c49d9013; Domain=.tiktok.com; Path=/; Secure; Expires=1811760358; tt_csrf_token=R2BYlpRK-P2Qh-lO2NBUgdzZCG-vGFi7gkH8; Domain=.tiktok.com; Path=/; Secure; tt_chain_token=\"aljUYq5Z3u8APiqwo6JJjw==\"; Domain=.tiktok.com; Path=/; Secure; Expires=1796208358",
  "format": "bytevc1_1080p_398613-1 - 1080x1920",
  "_filename": "C:\\Users\\yulon\\Desktop\\Current Projects\\Social media analysis\\tiktok_analysis\\data\\yt_meta\\7644863912545881366",
  "filename": "C:\\Users\\yulon\\Desktop\\Current Projects\\Social media analysis\\tiktok_analysis\\data\\yt_meta\\7644863912545881366",
  "_type": "video",
  "_version": {
    "version": "2026.03.17",
    "current_git_head": null,
    "release_git_head": "04d6974f502bbdfaed72c624344f262e30ad9708",
    "repository": "yt-dlp/yt-dlp"
  }
}